smdb_api/__init__.py
smdb_api-0.13.7.dist-info/licenses/LICENSE
smdb_api-0.13.7.dist-info/METADATA
smdb_api-0.13.7.dist-info/WHEEL
smdb_api-0.13.7.dist-info/top_level.txt
smdb_api-0.13.7.dist-info/RECORD
