Metadata-Version: 2.4
Name: smdb_api
Version: 0.13.7
Summary: API package for Server Monitoring Discord Bot
Home-page: https://github.com/NightKey/smdb-api
Author: Janthó Dávid
Author-email: davidjantho@gmail.com
Project-URL: Bug Tracker, https://github.com/NightKey/smdb-api/issues
Classifier: Development Status :: 4 - Beta
Classifier: Programming Language :: Python :: 3
Classifier: License :: Freeware
Classifier: Operating System :: OS Independent
Requires-Python: >=3.7
License-File: LICENSE
Dynamic: license-file
